__init__.py
HM/__init__.py
HM/__project__.py
HM/framework.py
HM/main.py
HM/globals/__init__.py
HM/globals/constants.py
HM/globals/paths.py
HM/jobs/__init__.py
HM/jobs/buffers.py
HM/jobs/histories.py
HM/jobs/jobs.py
HM/jobs/workflows.py
HM/jobs/actions/__init__.py
HM/jobs/actions/video/__init__.py
HM/jobs/actions/video/extractors/__init__.py
HM/jobs/actions/video/extractors/frames.py
HM/operators/__init__.py
HM/operators/counter.py
HM/setup/__init__.py
HM/setup/configuration/__init__.py
HM/setup/configuration/variables.py
hm_framework-0.0.1.dist-info/METADATA
hm_framework-0.0.1.dist-info/WHEEL
hm_framework-0.0.1.dist-info/top_level.txt
hm_framework-0.0.1.dist-info/RECORD
