Metadata-Version: 2.1
Name: hm-framework
Version: 0.0.1
Summary: Hugin & Munin Framework
Author-email: Kent vejrup Madsen <Kent.vejrup.Madsen@outlook.com>
Project-URL: Homepage, https://github.com/KentVejrupMadsen/HM.Framework
Project-URL: Bug Tracker, https://github.com/KentVejrupMadsen/HM.Framework/issues
Classifier: Programming Language :: Python :: 3
Classifier: Operating System :: OS Independent
Requires-Python: >=3.7
